htmltextconvert/__init__.py
htmltextconvert/convert.py
htmltextconvert/htmlstreamer.py
htmltextconvert/test_convert.py
htmltextconvert/test_htmlstreamer.py
htmltextconvert-0.1.2.dist-info/DESCRIPTION.rst
htmltextconvert-0.1.2.dist-info/METADATA
htmltextconvert-0.1.2.dist-info/RECORD
htmltextconvert-0.1.2.dist-info/WHEEL
htmltextconvert-0.1.2.dist-info/metadata.json
htmltextconvert-0.1.2.dist-info/top_level.txt
