Metadata-Version: 2.0
Name: htmltextconvert
Version: 0.1.2
Summary: Convert HTML to plain text
Home-page: https://ollycope.com/repos/htmltextconvert
Author: Oliver Cope
Author-email: oliver@redgecko.org
License: Apache License 2.0
Platform: UNKNOWN
Classifier: Development Status :: 5 - Production/Stable
Classifier: Intended Audience :: Developers
Classifier: License :: OSI Approved :: Apache Software License
Classifier: Operating System :: OS Independent
Classifier: Programming Language :: Python :: 3
Classifier: Programming Language :: Python :: 3 :: Only
Classifier: Topic :: Text Processing
Classifier: Topic :: Text Processing :: Markup
